{
    "questionId": 603,
    "image": "data/images/q0603.webp",
    "translations": {
        "uz": {
            "text": "Текст вопроса не найден",
            "options": [
                "F1. Avtoxo'jalik rahbaridan yurishga ruxsat olishi kerak",
                "F2. DYHX xodimidan yurishga ruxsatnoma olishi kerak",
                "F3. Boshqa yo'nalish bo'yicha yo'l qismini aylanib o'tishi kerak"
            ],
            "correctAnswer": 3,
            "explanation": "YHQ 1-ilovasi 3-bo'limining oʻn beshinchi xatboshisiga asosan: 3.13. «Cheklangan balandlik». Gabarit balandligi (yuk bilan yoki yuksiz) belgida ko'rsatilganidan ortiq bo'lgan transport vositalarining harakatlanishi taqiqlanishini bildiradi."
        },
        "ru": {
            "text": "Текст вопроса не найден",
            "options": [
                "F1. Иметь разрешение на проезд от руководителя автохозяйства",
                "F2. Получить разрешение на проезд у ближайшего сотрудника ГСБДД",
                "F3. Объехать участок дороги по другому маршруту"
            ],
            "correctAnswer": 3,
            "explanation": "Запрещающий знак 3.13 \"Ограничение высоты\". Запрещается движение транспортных средств, габаритная высота которых (с грузом или без груза) больше указанной на знаке."
        },
        "uzk": {
            "text": "Текст вопроса не найден",
            "options": [
                "F1. Автохўжалик раҳбаридан юришга рухсат олиши керак",
                "F2. Дйхх ходимидан юришга рухсатнома олиши керак",
                "F3. Бошқа йўналиш бўйича йўл қисмини айланиб ўтиши керак"
            ],
            "correctAnswer": 3,
            "explanation": "ЙҲҚ 1-иловаси 3-бўлимининг ўн бешинчи хатбошисига асосан: 3.13. «Чекланган баландлик. Габарит баландлиги (юк билан ёки юксиз) белгида кўрсатилганидан ортиқ бўлган транспорт воситаларининг ҳаракатланиши тақиқланишини билдиради."
        }
    }
}