{
    "questionId":  633,
    "image":  "data/images/q0633.webp",
    "translations":  {
                         "uz":  {
                                    "text":  "Mazkur chiziq nimani bildiradi?",
                                    "options":  [
                                                    "F1. Harakat svetofor bilan tartibga solinadigan piyodalar o\u0027tish joyini",
                                                    "F2. Velosiped yo\u0027lkasining qatnov qismini kesib o\u0027tadigan joyni",
                                                    "F3. Piyodalar yo\u0027lkasining qatnov qismini kesib o\u0027tadigan joyni"
                                                ],
                                    "correctAnswer":  2,
                                    "explanation":  "YHQ 2-ilovasi 1-boʻlimining oʻn to\u0027qqizinchi xatboshisiga asosan: 1.15 — yo\u0027lning velosiped yo\u0027lkasi kesib oʻtgan joyini bildiradi."
                                },
                         "ru":  {
                                    "text":  "Что обозначает данная разметка?",
                                    "options":  [
                                                    "F1. Пешеходный переход, где движение регулируется светофором",
                                                    "F2. Место, где велосипедная дорожка пересекает проезжую часть",
                                                    "F3. Место, где пешеходная дорожка пересекает проезжую часть"
                                                ],
                                    "correctAnswer":  2,
                                    "explanation":  "Горизонтальная разметка 1.15 - обозначает место, где велосипедная дорожка пересекает проезжую часть."
                                },
                         "uzk":  {
                                     "text":  "Мазкур чизиқ нимани билдиради?",
                                     "options":  [
                                                     "F1. Ҳаракат светофор билан тартибга солинадиган пиёдалар ўтиш жойини",
                                                     "F2. Велосипед йўлкасининг қатнов қисмини кесиб ўтадиган жойни",
                                                     "F3. Пиёдалар йўлкасининг қатнов қисмини кесиб ўтадиган жойни"
                                                 ],
                                     "correctAnswer":  2,
                                     "explanation":  "ЙҲҚ 2-иловаси 1-бўлимининг ўн тўққизинчи хатбошисига асосан: 1.15 — йўлнинг велосипед йўлкаси кесиб ўтган жойини билдиради."
                                 }
                     }
}
