{
    "questionId": 943,
    "image": "data/images/defaultpic.jpg",
    "translations": {
        "uz": {
            "text": "108 km/soat tezlikda harakatlanayotgan avtomobil 1 sekundda qancha masofani bosib o'tadi?",
            "options": [
                "F1. 15 m",
                "F2. 30 m",
                "F3. 20 m"
            ],
            "correctAnswer": 2,
            "explanation": "1 km = 1000 metr\n1 soat = 60 min = 3600 sekund\nKeling, ushbu qiymatlarni almashtiramiz:\n108 km/soat = 108*1000/(1*3600) = 108000/3600 = 30 m/s."
        },
        "ru": {
            "text": "Какое расстояние проедет транспортное средство за одну секунду при скорости движения 108 км/ч?",
            "options": [
                "F1. 15 м",
                "F2. 30 м",
                "F3. 20 м"
            ],
            "correctAnswer": 2,
            "explanation": "1 км = 1000 метр\n1 ч = 60 мин = 3600 секунд\nПодставим данные значения:\n108 км/ч = 108*1000/(1*3600) = 108000/3600 = 30 м/с."
        },
        "uzk": {
            "text": "108 км/соат тезликда ҳаракатланаётган автомобиль 1 секундда қанча масофани босиб ўтади?",
            "options": [
                "F1. 15 м",
                "F2. 30 м",
                "F3. 20 м"
            ],
            "correctAnswer": 2,
            "explanation": "1 км = 1000 метр\n1 соат = 60 мин = 3600 секунд\nКелинг, ушбу қийматларни алмаштирамиз:\n108 км/соат = 108*1000/(1*3600) = 108000/3600 = 30 м/с."
        }
    }
}